anhaltai_commons_minio/__init__.py
anhaltai_commons_minio/bucket_utils.py
anhaltai_commons_minio/client_utils.py
anhaltai_commons_minio/helper_utils.py
anhaltai_commons_minio/io_utils.py
anhaltai_commons_minio/adapters/__init__.py
anhaltai_commons_minio/adapters/nextcloud.py
anhaltai_commons_minio-2025.3.5.dist-info/LICENSE
anhaltai_commons_minio-2025.3.5.dist-info/METADATA
anhaltai_commons_minio-2025.3.5.dist-info/WHEEL
anhaltai_commons_minio-2025.3.5.dist-info/top_level.txt
anhaltai_commons_minio-2025.3.5.dist-info/RECORD
