Metadata-Version: 2.2
Name: anhaltai-commons-minio
Version: 2025.3.5
Summary: AnhaltAI Commons Minio: Additional functions for using Minio
Author-email: Christian Hänig <christian.haenig@hs-anhalt.de>, Christian Gurski <christian.gurski@hs-anhalt.de>
Project-URL: Gitlab, https://gitlab.hs-anhalt.de/ki/projekte/anhaltai-commons/commons-minio
Project-URL: PyPI, https://pypi.org/project/anhaltai-commons-minio/
Classifier: Programming Language :: Python :: 3
Classifier: License :: OSI Approved :: MIT License
Classifier: Operating System :: OS Independent
Requires-Python: >=3.10
License-File: LICENSE
Requires-Dist: numpy~=1.26.0
Requires-Dist: minio~=7.2.9
Requires-Dist: numerize~=0.12
Requires-Dist: opencv-python-headless~=4.10.0
Requires-Dist: pandas~=2.2.2
Requires-Dist: python-dotenv~=1.0.1
Requires-Dist: tqdm~=4.66.4
Requires-Dist: urllib3~=2.2.1
Requires-Dist: requests~=2.32.3
Requires-Dist: nc_py_api~=0.17.1
Requires-Dist: pytest~=8.3.3
Requires-Dist: pytest-minio-mock~=0.4.16
Requires-Dist: pytest-mock~=3.14.0
